Topsis/102003736.py
Topsis/__init__.py
TOPSIS_Brahmjot_102003736-0.0.1.dist-info/METADATA
TOPSIS_Brahmjot_102003736-0.0.1.dist-info/WHEEL
TOPSIS_Brahmjot_102003736-0.0.1.dist-info/top_level.txt
TOPSIS_Brahmjot_102003736-0.0.1.dist-info/RECORD
