Metadata-Version: 2.1
Name: TOPSIS-Brahmjot-102003736
Version: 0.0.1
Summary: TOPSIS-Ranking Algorithm for Multiple Criteria Decision Making
Author: Brahmjot Kaur
Author-email: <brahmjotkaur2002@gmail.com >
Keywords: python,TOPSIS,MCDM,Ranking
Classifier: Development Status :: 1 - Planning
Classifier: Intended Audience :: Developers
Classifier: Programming Language :: Python :: 3
Classifier: Operating System :: Unix
Classifier: Operating System :: MacOS :: MacOS X
Classifier: Operating System :: Microsoft :: Windows
Requires-Dist: python
